violetear/__init__.py
violetear/animation.py
violetear/app.py
violetear/client.py
violetear/color.py
violetear/dom.py
violetear/helpers.py
violetear/icon.png
violetear/markup.py
violetear/media.py
violetear/normalize.css
violetear/presets.py
violetear/pwa.py
violetear/selector.py
violetear/storage.py
violetear/style.py
violetear/stylesheet.py
violetear/types.py
violetear/units.py
violetear-1.2.4.dist-info/METADATA
violetear-1.2.4.dist-info/WHEEL
violetear-1.2.4.dist-info/licenses/LICENSE
violetear-1.2.4.dist-info/RECORD
