Metadata-Version: 2.4
Name: violetear
Version: 1.2.4
Summary: Full-Stack Web Development Framework for Pythonistas
Author-email: Alejandro Piad <apiad@apiad.net>
License-File: LICENSE
Classifier: License :: OSI Approved :: MIT License
Classifier: Operating System :: OS Independent
Classifier: Programming Language :: Python :: 3.12
Classifier: Topic :: Software Development :: Libraries :: Application Frameworks
Requires-Python: >=3.12
Provides-Extra: server
Requires-Dist: fastapi[standard]>=0.124.0; extra == 'server'
